ipywidgets_bokeh/__init__.py
ipywidgets_bokeh/bokeh.ext.json
ipywidgets_bokeh/kernel.py
ipywidgets_bokeh/package.json
ipywidgets_bokeh/widget.py
ipywidgets_bokeh/dist/64.ipywidgets_bokeh.js
ipywidgets_bokeh/dist/87.ipywidgets_bokeh.js
ipywidgets_bokeh/dist/ipywidgets_bokeh.js
ipywidgets_bokeh/dist/lib/index.d.ts
ipywidgets_bokeh/dist/lib/index.js
ipywidgets_bokeh/dist/lib/loader.d.ts
ipywidgets_bokeh/dist/lib/loader.js
ipywidgets_bokeh/dist/lib/manager.d.ts
ipywidgets_bokeh/dist/lib/manager.js
ipywidgets_bokeh/dist/lib/webpack.d.ts
ipywidgets_bokeh/dist/lib/webpack.js
ipywidgets_bokeh/dist/lib/widget.d.ts
ipywidgets_bokeh/dist/lib/widget.js
ipywidgets_bokeh-1.6.0.dist-info/LICENSE.txt
ipywidgets_bokeh-1.6.0.dist-info/METADATA
ipywidgets_bokeh-1.6.0.dist-info/WHEEL
ipywidgets_bokeh-1.6.0.dist-info/top_level.txt
ipywidgets_bokeh-1.6.0.dist-info/RECORD
