Metadata-Version: 2.1
Name: ipywidgets_bokeh
Version: 1.6.0
Summary: Allows embedding of Jupyter widgets in Bokeh layouts.
Home-page: https://github.com/bokeh/ipywidgets_bokeh
Author: Bokeh Team
Author-email: info@bokeh.org
License: BSD-3-Clause
Classifier: License :: OSI Approved :: BSD License
Classifier: Development Status :: 5 - Production/Stable
Classifier: Programming Language :: Python :: 3.9
Classifier: Programming Language :: Python :: 3.10
Classifier: Programming Language :: Python :: 3.11
Classifier: Operating System :: OS Independent
Classifier: Intended Audience :: Science/Research
Classifier: Intended Audience :: Developers
Classifier: Natural Language :: English
Classifier: Topic :: Scientific/Engineering
Classifier: Topic :: Software Development :: Libraries
Requires-Python: >=3.9
License-File: LICENSE.txt
Requires-Dist: bokeh ==3.*
Requires-Dist: ipywidgets ==8.*
Requires-Dist: ipykernel !=6.18.0,==6.*
Provides-Extra: dev
Requires-Dist: anywidget >=0.3.0 ; extra == 'dev'
Requires-Dist: panel >=1.0.4 ; extra == 'dev'
Requires-Dist: pytest >=7.3.1 ; extra == 'dev'
Requires-Dist: pytest-cov >=4.1.0 ; extra == 'dev'
Requires-Dist: pytest-playwright >=0.3.3 ; extra == 'dev'
